ue04/1_zaehler/src/counter_ea_struct.vhd
library IEEE; 
use IEEE.STD_LOGIC_1164.all;

entity counter is
  generic (width: integer);
  port(clk, reset: in  std_ulogic;
       up:         in  std_ulogic;
       y:          out std_ulogic_vector(width-1 downto 0));
end;    

architecture struct of counter is
  
  
  
begin



end;

ue04/1_zaehler/tb/testbench.vhd
library IEEE;
use IEEE.STD_LOGIC_1164.all;
use IEEE.STD_LOGIC_UNSIGNED.all; 
use IEEE.NUMERIC_STD.all;

entity testbench is
end;

architecture test of testbench is

  component counter is
    generic(width: integer);
    port(clk, reset: in  std_ulogic;
          up:         in  std_ulogic;
          y:          out std_ulogic_vector(width-1 downto 0));
  end component;

  constant w_a: integer := 3;
  constant w_b: integer := 4;  
    
  signal clk, reset: std_ulogic := '0';
  signal up:         std_ulogic := '1';
  signal y_a:        std_ulogic_vector(w_a-1 downto 0);
  signal y_b:        std_ulogic_vector(w_b-1 downto 0);
  
begin
  -- initiate device to be tested
  four: counter generic map(width => w_a) port map(clk, reset, up, y_a);
  five: counter generic map(width => w_b) port map(clk, reset, up, y_b);
  
  -- generate clock with 10 ns period
  process begin
      report ("increment");
      for i in 1 to 32 loop
        clk <= not(clk);
        wait for 5 ps;
        clk <= not(clk);
        wait for 5 ps;
        report "The value of y_a=" & integer'image(to_integer(unsigned(y_a))) & "     y_b=" & integer'image(to_integer(unsigned(y_b)));
      end loop;
      wait for 5 ns;
      
      report ("decrement");
      up <= '0';
      for i in 1 to 32 loop
        clk <= not(clk);
        wait for 5 ps;
        clk <= not(clk);
        wait for 5 ps;
        report "The value of y_a=" & integer'image(to_integer(unsigned(y_a))) & "     y_b=" & integer'image(to_integer(unsigned(y_b)));
      end loop;
      wait for 5 ns;
      
      report ("up toggle");
      up <= '1';
      for i in 1 to 8 loop
        clk <= not(clk);
        wait for 5 ps;
        clk <= not(clk);
        wait for 5 ps;
        report "The value of y_a=" & integer'image(to_integer(unsigned(y_a))) & "     y_b=" & integer'image(to_integer(unsigned(y_b)));
        up <= not(up);
      end loop;
      wait;
    end process;

    -- test all combinations
    process begin
      reset <= '1';
      wait for 12 ps;
      reset <= '0';
      report("reset released");
      wait;
   end process;
end;

ue04/1_zaehler/sim/result.vcd
$date
  Wed Apr  9 21:48:42 2025
$end
$version
  GHDL v0
$end
$timescale
  1 fs
$end
$scope module standard $end
$upscope $end
$scope module textio $end
$upscope $end
$scope module std_logic_1164 $end
$upscope $end
$scope module std_logic_arith $end
$upscope $end
$scope module std_logic_unsigned $end
$upscope $end
$scope module numeric_std $end
$upscope $end
$scope module testbench $end
$var reg 1 ! clk $end
$var reg 1 " reset $end
$var reg 1 # up $end
$var reg 3 $ y_a[2:0] $end
$var reg 4 % y_b[3:0] $end
$scope module four $end
$var reg 1 & clk $end
$var reg 1 ' reset $end
$var reg 1 ( up $end
$var reg 3 ) y[2:0] $end
$upscope $end
$scope module five $end
$var reg 1 * clk $end
$var reg 1 + reset $end
$var reg 1 , up $end
$var reg 4 - y[3:0] $end
$upscope $end
$upscope $end
$enddefinitions $end
#0
1!
1"
1#
bUUU $
bUUUU %
1&
1'
1(
bUUU )
1*
1+
1,
bUUUU -
#5000
0!
0&
0*
#10000
1!
1&
1*
#12000
0"
0'
0+
#15000
0!
0&
0*
#20000
1!
1&
1*
#25000
0!
0&
0*
#30000
1!
1&
1*
#35000
0!
0&
0*
#40000
1!
1&
1*
#45000
0!
0&
0*
#50000
1!
1&
1*
#55000
0!
0&
0*
#60000
1!
1&
1*
#65000
0!
0&
0*
#70000
1!
1&
1*
#75000
0!
0&
0*
#80000
1!
1&
1*
#85000
0!
0&
0*
#90000
1!
1&
1*
#95000
0!
0&
0*
#100000
1!
1&
1*
#105000
0!
0&
0*
#110000
1!
1&
1*
#115000
0!
0&
0*
#120000
1!
1&
1*
#125000
0!
0&
0*
#130000
1!
1&
1*
#135000
0!
0&
0*
#140000
1!
1&
1*
#145000
0!
0&
0*
#150000
1!
1&
1*
#155000
0!
0&
0*
#160000
1!
1&
1*
#165000
0!
0&
0*
#170000
1!
1&
1*
#175000
0!
0&
0*
#180000
1!
1&
1*
#185000
0!
0&
0*
#190000
1!
1&
1*
#195000
0!
0&
0*
#200000
1!
1&
1*
#205000
0!
0&
0*
#210000
1!
1&
1*
#215000
0!
0&
0*
#220000
1!
1&
1*
#225000
0!
0&
0*
#230000
1!
1&
1*
#235000
0!
0&
0*
#240000
1!
1&
1*
#245000
0!
0&
0*
#250000
1!
1&
1*
#255000
0!
0&
0*
#260000
1!
1&
1*
#265000
0!
0&
0*
#270000
1!
1&
1*
#275000
0!
0&
0*
#280000
1!
1&
1*
#285000
0!
0&
0*
#290000
1!
1&
1*
#295000
0!
0&
0*
#300000
1!
1&
1*
#305000
0!
0&
0*
#310000
1!
1&
1*
#315000
0!
0&
0*
#320000
#5320000
1!
0#
1&
0(
1*
0,
#5325000
0!
0&
0*
#5330000
1!
1&
1*
#5335000
0!
0&
0*
#5340000
1!
1&
1*
#5345000
0!
0&
0*
#5350000
1!
1&
1*
#5355000
0!
0&
0*
#5360000
1!
1&
1*
#5365000
0!
0&
0*
#5370000
1!
1&
1*
#5375000
0!
0&
0*
#5380000
1!
1&
1*
#5385000
0!
0&
0*
#5390000
1!
1&
1*
#5395000
0!
0&
0*
#5400000
1!
1&
1*
#5405000
0!
0&
0*
#5410000
1!
1&
1*
#5415000
0!
0&
0*
#5420000
1!
1&
1*
#5425000
0!
0&
0*
#5430000
1!
1&
1*
#5435000
0!
0&
0*
#5440000
1!
1&
1*
#5445000
0!
0&
0*
#5450000
1!
1&
1*
#5455000
0!
0&
0*
#5460000
1!
1&
1*
#5465000
0!
0&
0*
#5470000
1!
1&
1*
#5475000
0!
0&
0*
#5480000
1!
1&
1*
#5485000
0!
0&
0*
#5490000
1!
1&
1*
#5495000
0!
0&
0*
#5500000
1!
1&
1*
#5505000
0!
0&
0*
#5510000
1!
1&
1*
#5515000
0!
0&
0*
#5520000
1!
1&
1*
#5525000
0!
0&
0*
#5530000
1!
1&
1*
#5535000
0!
0&
0*
#5540000
1!
1&
1*
#5545000
0!
0&
0*
#5550000
1!
1&
1*
#5555000
0!
0&
0*
#5560000
1!
1&
1*
#5565000
0!
0&
0*
#5570000
1!
1&
1*
#5575000
0!
0&
0*
#5580000
1!
1&
1*
#5585000
0!
0&
0*
#5590000
1!
1&
1*
#5595000
0!
0&
0*
#5600000
1!
1&
1*
#5605000
0!
0&
0*
#5610000
1!
1&
1*
#5615000
0!
0&
0*
#5620000
1!
1&
1*
#5625000
0!
0&
0*
#5630000
1!
1&
1*
#5635000
0!
0&
0*
#5640000
#10640000
1!
1#
1&
1(
1*
1,
#10645000
0!
0&
0*
#10650000
1!
0#
1&
0(
1*
0,
#10655000
0!
0&
0*
#10660000
1!
1#
1&
1(
1*
1,
#10665000
0!
0&
0*
#10670000
1!
0#
1&
0(
1*
0,
#10675000
0!
0&
0*
#10680000
1!
1#
1&
1(
1*
1,
#10685000
0!
0&
0*
#10690000
1!
0#
1&
0(
1*
0,
#10695000
0!
0&
0*
#10700000
1!
1#
1&
1(
1*
1,
#10705000
0!
0&
0*
#10710000
1!
0#
1&
0(
1*
0,
#10715000
0!
0&
0*
#10720000
1#
1(
1,
