ue03/template/3_alu/src/alu_ea_struct.vhd
library IEEE;
use IEEE.NUMERIC_STD.all; -- habe mir die Vergleiche in dem Testfile angeschaut

use IEEE.STD_LOGIC_1164.all;
entity alu is
  generic(width: integer := 32);
  port(a, b:      in     std_ulogic_vector(width-1 downto 0);
       mode:      in     std_ulogic_vector(2 downto 0);
       result:    buffer std_ulogic_vector(width-1 downto 0);
       neg: buffer std_ulogic);
end entity alu;

library IEEE;
use IEEE.STD_LOGIC_1164.all;
entity fa is
  port(a, b, cin: in  std_ulogic;
       cout, s:   out std_ulogic);
end entity fa;

architecture struct of fa is
begin
    cout <= (a and b) or (a and cin) or (b and cin);
    s <= a xor b xor cin;
end architecture struct;

library IEEE;
use IEEE.STD_LOGIC_1164.all;
entity cra_gen is
  generic(width: integer := 32);
  port(a, b: in  std_ulogic_vector(width-1 downto 0);
       cin:  in  std_ulogic;
       cout: out std_ulogic;
       sum:  out std_ulogic_vector(width-1 downto 0));
end entity cra_gen;    

architecture struct of cra_gen is
  component fa --Wiederholung der Komponent damit wir sie nutzen können
    port(a, b, cin: in  std_ulogic;
         cout, s:   out std_ulogic);
  end component;
--    signal c1, c2, c3: STD_ULOGIC; -- mit den Signalen verbinden wir Cout und Cin der FAs
  signal c: std_ulogic_vector(width-1 downto 0);
begin
  
  fa0: fa port map(a(0), b(0), cin, c(0), sum(0));
  
  FA_CHAIN: for I in 1 to width-1 generate
    faN: fa port map(a(I), b(I), c(I-1), c(I), sum(I));
  end generate;
  
  cout <= c(width-1);
end architecture struct;

architecture struct of alu is
component cra_gen is
 port(a, b: in  std_ulogic_vector(width-1 downto 0);
       cin:  in  std_ulogic;
       cout: out std_ulogic;
       sum:  out std_ulogic_vector(width-1 downto 0));
end component cra_gen;


signal result_signal: std_ulogic_vector(width -1 downto 0);
signal sum_result: std_ulogic_vector(width -1 downto 0);
signal cin_modified: std_ulogic := '0'; -- 
signal b_modified: std_ulogic_vector(width -1 downto 0);
signal c_out_for_nothing:std_ulogic;
signal neg_value:std_ulogic;

begin
  adder: cra_gen port map(
    a,
    b_modified,
    cin_modified,
    c_out_for_nothing,
    sum_result
  );

  process(a,b,mode,sum_result)

  begin
  b_modified <= b;
  cin_modified <= '0';
  report "a: " & to_string(a);
  report "b_modified: " & to_string(b_modified);
      if mode = "000" then
      result_signal <= a or b;
      end if; 
      if mode = "001" then
      result_signal <= a and b; 
      end if;

      if mode = "010" then
        
         b_modified <=  b;
               report " AFTER _UPDATE Mode: 010 | b_modified = " & to_string(b_modified);

         cin_modified <= '0';
         result_signal <= sum_result;
              end if;
      if mode = "100" then
      result_signal <= a or not b;
      end if;

      if mode = "101" then
      result_signal <= a and not b;
      end if;

      if mode = "110" then
            cin_modified <= '1';
            b_modified <= not b;
           result_signal <= sum_result;
      end if;
    if mode = "111" then
         

          if signed(a) < signed(b) then
              result_signal <= (0 => '1', others => '0');
           else 
            result_signal <= (0 => '0', others  => '0' );
        end if;
      end if;

  report "MSB (bit 31) of result_signal = " & std_logic'image(result_signal(31));
  end process;
  result <= result_signal;
  neg <= result_signal(width - 1);
end;

ue03/template/3_alu/tb/testbench.vhd
library IEEE;
use IEEE.STD_LOGIC_1164.all;
use IEEE.NUMERIC_STD.all;

entity testbench is
end;

architecture test of testbench is
  component ALU
    generic(width: integer := 32);
    port(a, b:      in     std_ulogic_vector(width-1 downto 0);
         mode:      in     std_ulogic_vector(2 downto 0);
         result:    buffer std_ulogic_vector(width-1 downto 0);
         neg: buffer std_ulogic);
  end component;

  constant width: integer := 32;
  
  signal a, b, y:  std_ulogic_vector(width-1 downto 0) := (others => '0');
  signal f: std_ulogic_vector(2 downto 0) := (others => '0');
  signal neg: std_ulogic := '0';

begin
  
  my_alu: ALU generic map(width) port map(a, b, f, y, neg);

  process begin
    report "-- TRIAL CHECKS --";
    a <= std_ulogic_vector(to_signed(1, a'length));
    b <= std_ulogic_vector(to_signed(5, b'length));
    wait for 40 ns;
    report "A = " & integer'image(to_integer(signed(a))) & ", B = " & integer'image(to_integer(signed(b)));
    
    f <= "000";
    wait for 40 ns;
    report "---------------------------------------------------";
    report "A OR B = " & integer'image(to_integer(signed(y)))
      & ", neg = " & std_ulogic'image(neg);

    f <= "001";
    wait for 40 ns;
    report "---------------------------------------------------";
    report "A AND B = " & integer'image(to_integer(signed(y)))
      & ", neg = " & std_ulogic'image(neg);
    
    f <= "010";
    wait for 40 ns;
    report "---------------------------------------------------";
    report "A + B = " & integer'image(to_integer(signed(y)))
      & ", neg = " & std_ulogic'image(neg);

    f <= "100";
    wait for 40 ns;
    report "---------------------------------------------------";
    report "A OR (NOT B) = " & integer'image(to_integer(signed(y)))
      & ", neg = " & std_ulogic'image(neg);

    f <= "101";
    wait for 40 ns;
    report "---------------------------------------------------";
    report "A AND (NOT B) = " & integer'image(to_integer(signed(y)))
      & ", neg = " & std_ulogic'image(neg);

    f <= "110";
    wait for 40 ns;
    report "---------------------------------------------------";
    report "A - B = " & integer'image(to_integer(signed(y)))
      & ", neg = " & std_ulogic'image(neg);

    f <= "111";
    wait for 40 ns;
    report "---------------------------------------------------";
    report "SLT = " & integer'image(to_integer(signed(y)))
      & ", neg = " & std_ulogic'image(neg);

    report "---------------------------------------------------";
    report "---------------------------------------------------";
    a <= std_ulogic_vector(to_signed(-4, a'length));
    b <= std_ulogic_vector(to_signed(2, b'length));
    wait for 40 ns;
    report "A = " & integer'image(to_integer(signed(a))) & ", B = " & integer'image(to_integer(signed(b)));
    
    f <= "000";
    wait for 40 ns;
    report "---------------------------------------------------";
    report "A OR B = " & integer'image(to_integer(signed(y)))
      & ", neg = " & std_ulogic'image(neg);

    f <= "001";
    wait for 40 ns;
    report "---------------------------------------------------";
    report "A AND B = " & integer'image(to_integer(signed(y)))
      & ", neg = " & std_ulogic'image(neg);
    
    f <= "010";
    wait for 40 ns;
    report "---------------------------------------------------";
    report "A + B = " & integer'image(to_integer(signed(y)))
      & ", neg = " & std_ulogic'image(neg);

    f <= "100";
    wait for 40 ns;
    report "---------------------------------------------------";
    report "A OR (NOT B) = " & integer'image(to_integer(signed(y)))
      & ", neg = " & std_ulogic'image(neg);

    f <= "101";
    wait for 40 ns;
    report "---------------------------------------------------";
    report "A AND (NOT B) = " & integer'image(to_integer(signed(y)))
      & ", neg = " & std_ulogic'image(neg);

    f <= "110";
    wait for 40 ns;
    report "---------------------------------------------------";
    report "A - B = " & integer'image(to_integer(signed(y)))
      & ", neg = " & std_ulogic'image(neg);

    f <= "111";
    wait for 40 ns;
    report "---------------------------------------------------";
    report "SLT = " & integer'image(to_integer(signed(y)))
      & ", neg = " & std_ulogic'image(neg);
    
    report "-- ERROR CHECKS --";
    for aa in -20 to 20 loop
      for bb in -20 to 20 loop
        a <= std_ulogic_vector(to_signed(aa, a'length));
        b <= std_ulogic_vector(to_signed(bb, b'length));

        f <= "000";
        wait for 5 ns;
        if((a or b) /= y) then
          report integer'image(aa) & " OR " & integer'image(bb) & " = " & integer'image(to_integer(signed(a or b))) & ", but y = " & integer'image(to_integer(signed(y))) & " (BREAK)" severity error;
          wait;
        end if;
        if(( to_integer(signed(y)) < 0 and (neg /= '1')) or (to_integer(signed(y)) >= 0 and neg /= '0')) then
          report "[a: " & integer'image(to_integer(signed(a))) & ", b:" & integer'image(to_integer(signed(b))) & ", op: " & integer'image(to_integer(unsigned(f))) & "] y is " & integer'image(to_integer(signed(y))) & ", but neg = " & std_ulogic'image(neg) & " (BREAK)" severity error;
          wait;
        end if;

        f <= "001";
        wait for 5 ns;
        if((a and b) /= y) then
          report integer'image(aa) & " AND " & integer'image(bb) & " = " & integer'image(to_integer(signed(a and b))) & ", but y = " & integer'image(to_integer(signed(y))) & " (BREAK)" severity error;
          wait;
        end if;
        if(( to_integer(signed(y)) < 0 and (neg /= '1')) or (to_integer(signed(y)) >= 0 and neg /= '0')) then
          report "[a: " & integer'image(to_integer(signed(a))) & ", b:" & integer'image(to_integer(signed(b))) & ", op: " & integer'image(to_integer(unsigned(f))) & "] y is " & integer'image(to_integer(signed(y))) & ", but neg = " & std_ulogic'image(neg) & " (BREAK)" severity error;
          wait;
        end if;

        f <= "010";
        wait for 5 ns;
        if(aa + bb /= to_integer(signed(y))) then
          report integer'image(aa) & " + " & integer'image(bb) & " = " & integer'image((aa + bb)) & ", but y = "  & integer'image(to_integer(signed(y))) & " (BREAK)" severity error;
          wait;
        end if;
        if(( to_integer(signed(y)) < 0 and (neg /= '1')) or (to_integer(signed(y)) >= 0 and neg /= '0')) then
          report "[a: " & integer'image(to_integer(signed(a))) & ", b:" & integer'image(to_integer(signed(b))) & ", op: " & integer'image(to_integer(unsigned(f))) & "] y is " & integer'image(to_integer(signed(y))) & ", but neg = " & std_ulogic'image(neg) & " (BREAK)" severity error;
          wait;
        end if;

        f <= "100";
        wait for 5 ns;
        if((a or (not b)) /= y) then
          report integer'image(aa) & " OR (NOT" & integer'image(bb) & ") = " & integer'image(to_integer(signed(a or (not b)))) & ", but y = " & integer'image(to_integer(signed(y))) & " (BREAK)" severity error;
          wait;
        end if;
        if(( to_integer(signed(y)) < 0 and (neg /= '1')) or (to_integer(signed(y)) >= 0 and neg /= '0')) then
          report "[a: " & integer'image(to_integer(signed(a))) & ", b:" & integer'image(to_integer(signed(b))) & ", op: " & integer'image(to_integer(unsigned(f))) & "] y is " & integer'image(to_integer(signed(y))) & ", but neg = " & std_ulogic'image(neg) & " (BREAK)" severity error;
          wait;
        end if;

        f <= "101";
        wait for 5 ns;
        if((a and (not b)) /= y) then
          report integer'image(aa) & " AND (NOT" & integer'image(bb) & ") = " & integer'image(to_integer(signed(a and (not b)))) & ", but y = "  & integer'image(to_integer(signed(y))) & " (BREAK)" severity error;
          wait;
        end if;
        if(( to_integer(signed(y)) < 0 and (neg /= '1')) or (to_integer(signed(y)) >= 0 and neg /= '0')) then
          report "[a: " & integer'image(to_integer(signed(a))) & ", b:" & integer'image(to_integer(signed(b))) & ", op: " & integer'image(to_integer(unsigned(f))) & "] y is " & integer'image(to_integer(signed(y))) & ", but neg = " & std_ulogic'image(neg) & " (BREAK)" severity error;
          wait;
        end if;

        f <= "110";
        wait for 5 ns;
        if(aa - bb /= to_integer(signed(y))) then
          report integer'image(aa) & " - " & integer'image(bb) & " = " & integer'image((aa - bb)) & ", but y = "  & integer'image(to_integer(signed(y))) & " (BREAK)" severity error;
          wait;
        end if;
        if(( to_integer(signed(y)) < 0 and (neg /= '1')) or (to_integer(signed(y)) >= 0 and neg /= '0')) then
          report "[a: " & integer'image(to_integer(signed(a))) & ", b:" & integer'image(to_integer(signed(b))) & "] y is " & integer'image(to_integer(signed(y))) & ", but neg = " & std_ulogic'image(neg) & " (BREAK)" severity error;
          wait;
        end if;

        f <= "111";
        wait for 5 ns;
        if(((aa < bb) and (to_integer(signed(y)) /= 1)) or ((aa >= bb) and (to_integer(signed(y)) /= 0))) then
          report integer'image(aa) & " < " & integer'image(bb) & " = " & integer'image(to_integer(signed(y))) & " (BREAK)" severity error;
          wait;
        end if;
        if(( to_integer(signed(y)) < 0 and (neg /= '1')) or (to_integer(signed(y)) >= 0 and neg /= '0')) then
          report "[a: " & integer'image(to_integer(signed(a))) & ", b:" & integer'image(to_integer(signed(b))) & ", op: " & integer'image(to_integer(unsigned(f))) & "] y is " & integer'image(to_integer(signed(y))) & ", but neg = " & std_ulogic'image(neg) & " (BREAK)" severity error;
          wait;
        end if;

        wait for 5 ns;
      end loop;
    end loop;
    report ("all done");
    wait;
  end process;
end;

ue03/template/3_alu/sim/result.vcd
$date
  Thu Apr  3 05:25:51 2025
$end
$version
  GHDL v0
$end
$timescale
  1 fs
$end
$scope module standard $end
$upscope $end
$scope module textio $end
$upscope $end
$scope module std_logic_1164 $end
$upscope $end
$scope module numeric_std $end
$upscope $end
$scope module testbench $end
$var reg 32 ! a[31:0] $end
$var reg 32 " b[31:0] $end
$var reg 32 # y[31:0] $end
$var reg 3 $ f[2:0] $end
$var reg 1 % neg $end
$scope module my_alu $end
$var reg 32 & a[31:0] $end
$var reg 32 ' b[31:0] $end
$var reg 3 ( mode[2:0] $end
$var reg 32 ) result[31:0] $end
$var reg 1 * neg $end
$var reg 32 + result_signal[31:0] $end
$var reg 32 , sum_result[31:0] $end
$var reg 1 - cin_modified $end
$var reg 32 . b_modified[31:0] $end
$var reg 1 / c_out_for_nothing $end
$var reg 1 0 neg_value $end
$scope module adder $end
$var reg 32 1 a[31:0] $end
$var reg 32 2 b[31:0] $end
$var reg 1 3 cin $end
$var reg 1 4 cout $end
$var reg 32 5 sum[31:0] $end
$var reg 32 6 c[31:0] $end
$scope module fa0 $end
$var reg 1 7 a $end
$var reg 1 8 b $end
$var reg 1 9 cin $end
$var reg 1 : cout $end
$var reg 1 ; s $end
$upscope $end
$scope module fa_chain(1) $end
$scope module fan $end
$var reg 1 < a $end
$var reg 1 = b $end
$var reg 1 > cin $end
$var reg 1 ? cout $end
$var reg 1 @ s $end
$upscope $end
$upscope $end
$scope module fa_chain(2) $end
$scope module fan $end
$var reg 1 A a $end
$var reg 1 B b $end
$var reg 1 C cin $end
$var reg 1 D cout $end
$var reg 1 E s $end
$upscope $end
$upscope $end
$scope module fa_chain(3) $end
$scope module fan $end
$var reg 1 F a $end
$var reg 1 G b $end
$var reg 1 H cin $end
$var reg 1 I cout $end
$var reg 1 J s $end
$upscope $end
$upscope $end
$scope module fa_chain(4) $end
$scope module fan $end
$var reg 1 K a $end
$var reg 1 L b $end
$var reg 1 M cin $end
$var reg 1 N cout $end
$var reg 1 O s $end
$upscope $end
$upscope $end
$scope module fa_chain(5) $end
$scope module fan $end
$var reg 1 P a $end
$var reg 1 Q b $end
$var reg 1 R cin $end
$var reg 1 S cout $end
$var reg 1 T s $end
$upscope $end
$upscope $end
$scope module fa_chain(6) $end
$scope module fan $end
$var reg 1 U a $end
$var reg 1 V b $end
$var reg 1 W cin $end
$var reg 1 X cout $end
$var reg 1 Y s $end
$upscope $end
$upscope $end
$scope module fa_chain(7) $end
$scope module fan $end
$var reg 1 Z a $end
$var reg 1 [ b $end
$var reg 1 \ cin $end
$var reg 1 ] cout $end
$var reg 1 ^ s $end
$upscope $end
$upscope $end
$scope module fa_chain(8) $end
$scope module fan $end
$var reg 1 _ a $end
$var reg 1 ` b $end
$var reg 1 a cin $end
$var reg 1 b cout $end
$var reg 1 c s $end
$upscope $end
$upscope $end
$scope module fa_chain(9) $end
$scope module fan $end
$var reg 1 d a $end
$var reg 1 e b $end
$var reg 1 f cin $end
$var reg 1 g cout $end
$var reg 1 h s $end
$upscope $end
$upscope $end
$scope module fa_chain(10) $end
$scope module fan $end
$var reg 1 i a $end
$var reg 1 j b $end
$var reg 1 k cin $end
$var reg 1 l cout $end
$var reg 1 m s $end
$upscope $end
$upscope $end
$scope module fa_chain(11) $end
$scope module fan $end
$var reg 1 n a $end
$var reg 1 o b $end
$var reg 1 p cin $end
$var reg 1 q cout $end
$var reg 1 r s $end
$upscope $end
$upscope $end
$scope module fa_chain(12) $end
$scope module fan $end
$var reg 1 s a $end
$var reg 1 t b $end
$var reg 1 u cin $end
$var reg 1 v cout $end
$var reg 1 w s $end
$upscope $end
$upscope $end
$scope module fa_chain(13) $end
$scope module fan $end
$var reg 1 x a $end
$var reg 1 y b $end
$var reg 1 z cin $end
$var reg 1 { cout $end
$var reg 1 | s $end
$upscope $end
$upscope $end
$scope module fa_chain(14) $end
$scope module fan $end
$var reg 1 } a $end
$var reg 1 !" b $end
$var reg 1 "" cin $end
$var reg 1 #" cout $end
$var reg 1 $" s $end
$upscope $end
$upscope $end
$scope module fa_chain(15) $end
$scope module fan $end
$var reg 1 %" a $end
$var reg 1 &" b $end
$var reg 1 '" cin $end
$var reg 1 (" cout $end
$var reg 1 )" s $end
$upscope $end
$upscope $end
$scope module fa_chain(16) $end
$scope module fan $end
$var reg 1 *" a $end
$var reg 1 +" b $end
$var reg 1 ," cin $end
$var reg 1 -" cout $end
$var reg 1 ." s $end
$upscope $end
$upscope $end
$scope module fa_chain(17) $end
$scope module fan $end
$var reg 1 /" a $end
$var reg 1 0" b $end
$var reg 1 1" cin $end
$var reg 1 2" cout $end
$var reg 1 3" s $end
$upscope $end
$upscope $end
$scope module fa_chain(18) $end
$scope module fan $end
$var reg 1 4" a $end
$var reg 1 5" b $end
$var reg 1 6" cin $end
$var reg 1 7" cout $end
$var reg 1 8" s $end
$upscope $end
$upscope $end
$scope module fa_chain(19) $end
$scope module fan $end
$var reg 1 9" a $end
$var reg 1 :" b $end
$var reg 1 ;" cin $end
$var reg 1 <" cout $end
$var reg 1 =" s $end
$upscope $end
$upscope $end
$scope module fa_chain(20) $end
$scope module fan $end
$var reg 1 >" a $end
$var reg 1 ?" b $end
$var reg 1 @" cin $end
$var reg 1 A" cout $end
$var reg 1 B" s $end
$upscope $end
$upscope $end
$scope module fa_chain(21) $end
$scope module fan $end
$var reg 1 C" a $end
$var reg 1 D" b $end
$var reg 1 E" cin $end
$var reg 1 F" cout $end
$var reg 1 G" s $end
$upscope $end
$upscope $end
$scope module fa_chain(22) $end
$scope module fan $end
$var reg 1 H" a $end
$var reg 1 I" b $end
$var reg 1 J" cin $end
$var reg 1 K" cout $end
$var reg 1 L" s $end
$upscope $end
$upscope $end
$scope module fa_chain(23) $end
$scope module fan $end
$var reg 1 M" a $end
$var reg 1 N" b $end
$var reg 1 O" cin $end
$var reg 1 P" cout $end
$var reg 1 Q" s $end
$upscope $end
$upscope $end
$scope module fa_chain(24) $end
$scope module fan $end
$var reg 1 R" a $end
$var reg 1 S" b $end
$var reg 1 T" cin $end
$var reg 1 U" cout $end
$var reg 1 V" s $end
$upscope $end
$upscope $end
$scope module fa_chain(25) $end
$scope module fan $end
$var reg 1 W" a $end
$var reg 1 X" b $end
$var reg 1 Y" cin $end
$var reg 1 Z" cout $end
$var reg 1 [" s $end
$upscope $end
$upscope $end
$scope module fa_chain(26) $end
$scope module fan $end
$var reg 1 \" a $end
$var reg 1 ]" b $end
$var reg 1 ^" cin $end
$var reg 1 _" cout $end
$var reg 1 `" s $end
$upscope $end
$upscope $end
$scope module fa_chain(27) $end
$scope module fan $end
$var reg 1 a" a $end
$var reg 1 b" b $end
$var reg 1 c" cin $end
$var reg 1 d" cout $end
$var reg 1 e" s $end
$upscope $end
$upscope $end
$scope module fa_chain(28) $end
$scope module fan $end
$var reg 1 f" a $end
$var reg 1 g" b $end
$var reg 1 h" cin $end
$var reg 1 i" cout $end
$var reg 1 j" s $end
$upscope $end
$upscope $end
$scope module fa_chain(29) $end
$scope module fan $end
$var reg 1 k" a $end
$var reg 1 l" b $end
$var reg 1 m" cin $end
$var reg 1 n" cout $end
$var reg 1 o" s $end
$upscope $end
$upscope $end
$scope module fa_chain(30) $end
$scope module fan $end
$var reg 1 p" a $end
$var reg 1 q" b $end
$var reg 1 r" cin $end
$var reg 1 s" cout $end
$var reg 1 t" s $end
$upscope $end
$upscope $end
$scope module fa_chain(31) $end
$scope module fan $end
$var reg 1 u" a $end
$var reg 1 v" b $end
$var reg 1 w" cin $end
$var reg 1 x" cout $end
$var reg 1 y" s $end
$upscope $end
$upscope $end
$upscope $end
$upscope $end
$upscope $end
$enddefinitions $end
#0
b00000000000000000000000000000001 !
b00000000000000000000000000000101 "
b00000000000000000000000000000101 #
b000 $
0%
b00000000000000000000000000000001 &
b00000000000000000000000000000101 '
b000 (
b00000000000000000000000000000101 )
0*
b00000000000000000000000000000101 +
b00000000000000000000000000000110 ,
0-
b00000000000000000000000000000101 .
0/
U0
b00000000000000000000000000000001 1
b00000000000000000000000000000101 2
03
04
b00000000000000000000000000000110 5
b00000000000000000000000000000001 6
17
18
09
1:
0;
0<
0=
1>
0?
1@
0A
1B
0C
0D
1E
0F
0G
0H
0I
0J
0K
0L
0M
0N
0O
0P
0Q
0R
0S
0T
0U
0V
0W
0X
0Y
0Z
0[
0\
0]
0^
0_
0`
0a
0b
0c
0d
0e
0f
0g
0h
0i
0j
0k
0l
0m
0n
0o
0p
0q
0r
0s
0t
0u
0v
0w
0x
0y
0z
0{
0|
0}
0!"
0""
0#"
0$"
0%"
0&"
0'"
0("
0)"
0*"
0+"
0,"
0-"
0."
0/"
00"
01"
02"
03"
04"
05"
06"
07"
08"
09"
0:"
0;"
0<"
0="
0>"
0?"
0@"
0A"
0B"
0C"
0D"
0E"
0F"
0G"
0H"
0I"
0J"
0K"
0L"
0M"
0N"
0O"
0P"
0Q"
0R"
0S"
0T"
0U"
0V"
0W"
0X"
0Y"
0Z"
0["
0\"
0]"
0^"
0_"
0`"
0a"
0b"
0c"
0d"
0e"
0f"
0g"
0h"
0i"
0j"
0k"
0l"
0m"
0n"
0o"
0p"
0q"
0r"
0s"
0t"
0u"
0v"
0w"
0x"
0y"
#40000000
#80000000
b00000000000000000000000000000001 #
b001 $
b001 (
b00000000000000000000000000000001 )
b00000000000000000000000000000001 +
#120000000
b00000000000000000000000000000110 #
b010 $
b010 (
b00000000000000000000000000000110 )
b00000000000000000000000000000110 +
#160000000
b11111111111111111111111111111011 #
b100 $
1%
b100 (
b11111111111111111111111111111011 )
1*
b11111111111111111111111111111011 +
#200000000
b00000000000000000000000000000000 #
b101 $
0%
b101 (
b00000000000000000000000000000000 )
0*
b00000000000000000000000000000000 +
#240000000
b11111111111111111111111111111100 #
b110 $
1%
b110 (
b11111111111111111111111111111100 )
1*
b11111111111111111111111111111100 +
b11111111111111111111111111111100 ,
1-
b11111111111111111111111111111010 .
b11111111111111111111111111111010 2
13
b11111111111111111111111111111100 5
b00000000000000000000000000000011 6
08
19
1=
1?
0@
0B
1C
1E
1G
1J
1L
1O
1Q
1T
1V
1Y
1[
1^
1`
1c
1e
1h
1j
1m
1o
1r
1t
1w
1y
1|
1!"
1$"
1&"
1)"
1+"
1."
10"
13"
15"
18"
1:"
1="
1?"
1B"
1D"
1G"
1I"
1L"
1N"
1Q"
1S"
1V"
1X"
1["
1]"
1`"
1b"
1e"
1g"
1j"
1l"
1o"
1q"
1t"
1v"
1y"
#280000000
b00000000000000000000000000000001 #
b111 $
0%
b111 (
b00000000000000000000000000000001 )
0*
b00000000000000000000000000000001 +
b00000000000000000000000000000110 ,
0-
b00000000000000000000000000000101 .
b00000000000000000000000000000101 2
03
b00000000000000000000000000000110 5
b00000000000000000000000000000001 6
18
09
0=
0?
1@
1B
0C
0D
1E
0G
0H
0J
0L
0O
0Q
0T
0V
0Y
0[
0^
0`
0c
0e
0h
0j
0m
0o
0r
0t
0w
0y
0|
0!"
0$"
0&"
0)"
0+"
0."
00"
03"
05"
08"
0:"
0="
0?"
0B"
0D"
0G"
0I"
0L"
0N"
0Q"
0S"
0V"
0X"
0["
0]"
0`"
0b"
0e"
0g"
0j"
0l"
0o"
0q"
0t"
0v"
0y"
#320000000
b11111111111111111111111111111100 !
b00000000000000000000000000000010 "
b11111111111111111111111111111100 &
b00000000000000000000000000000010 '
b11111111111111111111111111111110 ,
b00000000000000000000000000000010 .
0/
b11111111111111111111111111111100 1
b00000000000000000000000000000010 2
04
b11111111111111111111111111111110 5
b00000000000000000000000000000000 6
07
08
0:
0;
1=
0>
1A
0B
0D
1E
1F
0H
0I
1J
1K
0M
0N
1O
1P
0R
0S
1T
1U
0W
0X
1Y
1Z
0\
0]
1^
1_
0a
0b
1c
1d
0f
0g
1h
1i
0k
0l
1m
1n
0p
0q
1r
1s
0u
0v
1w
1x
0z
0{
1|
1}
0""
0#"
1$"
1%"
0'"
0("
1)"
1*"
0,"
0-"
1."
1/"
01"
02"
13"
14"
06"
07"
18"
19"
0;"
0<"
1="
1>"
0@"
0A"
1B"
1C"
0E"
0F"
1G"
1H"
0J"
0K"
1L"
1M"
0O"
0P"
1Q"
1R"
0T"
0U"
1V"
1W"
0Y"
0Z"
1["
1\"
0^"
0_"
1`"
1a"
0c"
0d"
1e"
1f"
0h"
0i"
1j"
1k"
0m"
0n"
1o"
1p"
0r"
0s"
1t"
1u"
0w"
0x"
1y"
#360000000
b11111111111111111111111111111110 #
b000 $
1%
b000 (
b11111111111111111111111111111110 )
1*
b11111111111111111111111111111110 +
#400000000
b00000000000000000000000000000000 #
b001 $
0%
b001 (
b00000000000000000000000000000000 )
0*
b00000000000000000000000000000000 +
#440000000
b11111111111111111111111111111110 #
b010 $
1%
b010 (
b11111111111111111111111111111110 )
1*
b11111111111111111111111111111110 +
#480000000
b11111111111111111111111111111101 #
b100 $
b100 (
b11111111111111111111111111111101 )
b11111111111111111111111111111101 +
#520000000
b11111111111111111111111111111100 #
b101 $
b101 (
b11111111111111111111111111111100 )
b11111111111111111111111111111100 +
#560000000
b11111111111111111111111111111010 #
b110 $
1%
b110 (
b11111111111111111111111111111010 )
1*
b11111111111111111111111111111010 +
b11111111111111111111111111111010 ,
1-
b11111111111111111111111111111101 .
1/
b11111111111111111111111111111101 2
13
14
b11111111111111111111111111111010 5
b11111111111111111111111111111101 6
18
19
1:
0=
1>
1@
1B
1D
0E
1G
1H
1I
1J
1L
1M
1N
1O
1Q
1R
1S
1T
1V
1W
1X
1Y
1[
1\
1]
1^
1`
1a
1b
1c
1e
1f
1g
1h
1j
1k
1l
1m
1o
1p
1q
1r
1t
1u
1v
1w
1y
1z
1{
1|
1!"
1""
1#"
1$"
1&"
1'"
1("
1)"
1+"
1,"
1-"
1."
10"
11"
12"
13"
15"
16"
17"
18"
1:"
1;"
1<"
1="
1?"
1@"
1A"
1B"
1D"
1E"
1F"
1G"
1I"
1J"
1K"
1L"
1N"
1O"
1P"
1Q"
1S"
1T"
1U"
1V"
1X"
1Y"
1Z"
1["
1]"
1^"
1_"
1`"
1b"
1c"
1d"
1e"
1g"
1h"
1i"
1j"
1l"
1m"
1n"
1o"
1q"
1r"
1s"
1t"
1v"
1w"
1x"
1y"
#600000000
b00000000000000000000000000000001 #
b111 $
0%
b111 (
b00000000000000000000000000000001 )
0*
b00000000000000000000000000000001 +
b11111111111111111111111111111110 ,
0-
b00000000000000000000000000000010 .
0/
b00000000000000000000000000000010 2
03
04
b11111111111111111111111111111110 5
b00000000000000000000000000000000 6
08
09
0:
1=
0>
0?
1@
0B
0C
0D
1E
0G
0H
0I
1J
0L
0M
0N
1O
0Q
0R
0S
1T
0V
0W
0X
1Y
0[
0\
0]
1^
0`
0a
0b
1c
0e
0f
0g
1h
0j
0k
0l
1m
0o
0p
0q
1r
0t
0u
0v
1w
0y
0z
0{
1|
0!"
0""
0#"
1$"
0&"
0'"
0("
1)"
0+"
0,"
0-"
1."
00"
01"
02"
13"
05"
06"
07"
18"
0:"
0;"
0<"
1="
0?"
0@"
0A"
1B"
0D"
0E"
0F"
1G"
0I"
0J"
0K"
1L"
0N"
0O"
0P"
1Q"
0S"
0T"
0U"
1V"
0X"
0Y"
0Z"
1["
0]"
0^"
0_"
1`"
0b"
0c"
0d"
1e"
0g"
0h"
0i"
1j"
0l"
0m"
0n"
1o"
0q"
0r"
0s"
1t"
0v"
0w"
0x"
1y"
#640000000
b11111111111111111111111111101100 !
b11111111111111111111111111101100 "
b11111111111111111111111111101100 #
b000 $
1%
b11111111111111111111111111101100 &
b11111111111111111111111111101100 '
b000 (
b11111111111111111111111111101100 )
1*
b11111111111111111111111111101100 +
b11111111111111111111111111011000 ,
b11111111111111111111111111101100 .
1/
b11111111111111111111111111101100 1
b11111111111111111111111111101100 2
14
b11111111111111111111111111011000 5
b11111111111111111111111111101100 6
0=
0@
1B
1D
0E
1G
1H
1I
1J
0K
1M
1O
1Q
1S
0T
1V
1W
1X
1Y
1[
1\
1]
1^
1`
1a
1b
1c
1e
1f
1g
1h
1j
1k
1l
1m
1o
1p
1q
1r
1t
1u
1v
1w
1y
1z
1{
1|
1!"
1""
1#"
1$"
1&"
1'"
1("
1)"
1+"
1,"
1-"
1."
10"
11"
12"
13"
15"
16"
17"
18"
1:"
1;"
1<"
1="
1?"
1@"
1A"
1B"
1D"
1E"
1F"
1G"
1I"
1J"
1K"
1L"
1N"
1O"
1P"
1Q"
1S"
1T"
1U"
1V"
1X"
1Y"
1Z"
1["
1]"
1^"
1_"
1`"
1b"
1c"
1d"
1e"
1g"
1h"
1i"
1j"
1l"
1m"
1n"
1o"
1q"
1r"
1s"
1t"
1v"
1w"
1x"
1y"
#645000000
b001 $
b001 (
#650000000
b11111111111111111111111111011000 #
b010 $
b010 (
b11111111111111111111111111011000 )
b11111111111111111111111111011000 +
#655000000
b11111111111111111111111111111111 #
b100 $
b100 (
b11111111111111111111111111111111 )
b11111111111111111111111111111111 +
#660000000
b00000000000000000000000000000000 #
b101 $
0%
b101 (
b00000000000000000000000000000000 )
0*
b00000000000000000000000000000000 +
